{"events":[{"title":"zxzx czx","description":"zxc zxc zxc zxc","image":"https://lh3.googleusercontent.com/1oBZlizrWpasPTC-Z0f9i8RwS10IGHNpdj7tKipayj-2iecD4m9AVyvHBweTJti3jQS7kVJc58agXs8Q3dTIUkiwT57Fo7v9KYSDhARGbX82yUHmGEb-=rwa-s1023-e366","date":"2023-05-31","id":"99e1e207-58e9-4e1c-9f6e-8b13f18ba093"},{"title":"new3","description":"sadsad dasda sdsa  sad asd /n asdasdas \\n sadasd","image":"https://media.istockphoto.com/id/824660060/uk/%D1%84%D0%BE%D1%82%D0%BE/%D1%81%D0%BC%D0%B0%D0%B6%D0%B5%D0%BD%D1%96-%D1%85%D1%80%D1%83%D1%81%D1%82%D0%BA%D1%96-%D0%BA%D1%83%D1%80%D1%8F%D1%87%D1%96-%D0%BD%D0%B0%D0%B3%D0%B5%D1%82%D1%81%D0%B8-%D0%B7-%D0%BA%D0%B5%D1%82%D1%87%D1%83%D0%BF%D0%BE%D0%BC-%D0%BD%D0%B0-%D0%B1%D1%96%D0%BB%D1%96%D0%B9-%D0%B4%D0%BE%D1%88%D1%86%D1%96.jpg?s=612x612&w=is&k=20&c=Aqsa7hX5DfAEQZGXFoqaPwH0GyYwP9D8ntjfGx8pmM8=","date":"2023-06-04","id":"ff443d49-72f6-4d45-9478-bb90e7c63ba8"},{"title":"new2","description":"qweqweqweqweqw","image":"https://media.istockphoto.com/id/618209540/uk/%D1%84%D0%BE%D1%82%D0%BE/%D0%BA%D0%BE%D1%88%D0%B8%D0%BA-%D0%BA%D1%83%D1%80%D1%8F%D1%87%D0%B8%D1%85-%D0%BD%D0%B0%D0%B3%D0%B5%D1%82%D1%81%D1%96%D0%B2-%D0%B7-%D0%BA%D0%B8%D1%81%D0%BB%D0%BE-%D1%81%D0%BE%D0%BB%D0%BE%D0%B4%D0%BA%D0%B8%D0%BC-%D1%81%D0%BE%D1%83%D1%81%D0%BE%D0%BC.jpg?s=612x612&w=is&k=20&c=ojat-UAldHx2N0DQAnNOo1E1xSvO0rukkFi240aueMA=","date":"2023-05-31","id":"d6fdcdca-3814-4c79-b85a-a5a9cce29e4d"},{"id":"e1","title":"A dummy event","date":"2023-02-22","image":"https://blog.hubspot.de/hubfs/Germany/Blog_images/Optimize_Marketing%20Events%20DACH%202021.jpg","description":"Join this amazing event and connect with fellow developers."}]}